<menu>
    <item>
        <text>Moss 设置</text>
        <icon>moss</icon>
        <action>moss</action>
        <data>xml_settings/zh/moss</data>
    </item>
    <item>
        <text>开发者设置</text>
        <icon>cog</icon>
        <action>moss</action>
        <data>xml_settings/zh/developer</data>
    </item>
    <item>
        <text>测试视图</text>
        <icon>cog</icon>
        <action>moss</action>
        <data>xml_settings/zh/test</data>
    </item>
    <item>
        <text>测试列表</text>
        <icon>cog</icon>
        <action>moss</action>
        <data>xml_settings/zh/test_list</data>
    </item>
</menu> 